{"abilities":[{"ability":{"name":"levitate"},"is_hidden":false,"slot":1}],"game_indices":[{"version":{"name":"ruby"}},{"version":{"name":"sapphire"}},{"version":{"name":"emerald"}},{"version":{"name":"firered"}},{"version":{"name":"leafgreen"}},{"version":{"name":"diamond"}},{"version":{"name":"pearl"}},{"version":{"name":"platinum"}},{"version":{"name":"heartgold"}},{"version":{"name":"soulsilver"}},{"version":{"name":"black"}},{"version":{"name":"white"}},{"version":{"name":"black-2"}},{"version":{"name":"white-2"}}],"height":15,"id":344,"moves":[{"move":{"name":"headbutt"}},{"move":{"name":"double-edge"}},{"move":{"name":"ice-beam"}},{"move":{"name":"psybeam"}},{"move":{"name":"hyper-beam"}},{"move":{"name":"strength"}},{"move":{"name":"solar-beam"}},{"move":{"name":"earthquake"}},{"move":{"name":"dig"}},{"move":{"name":"toxic"}},{"move":{"name":"confusion"}},{"move":{"name":"psychic"}},{"move":{"name":"teleport"}},{"move":{"name":"mimic"}},{"move":{"name":"double-team"}},{"move":{"name":"harden"}},{"move":{"name":"light-screen"}},{"move":{"name":"reflect"}},{"move":{"name":"self-destruct"}},{"move":{"name":"dream-eater"}},{"move":{"name":"flash"}},{"move":{"name":"explosion"}},{"move":{"name":"rest"}},{"move":{"name":"rock-slide"}},{"move":{"name":"substitute"}},{"move":{"name":"snore"}},{"move":{"name":"protect"}},{"move":{"name":"mud-slap"}},{"move":{"name":"sandstorm"}},{"move":{"name":"endure"}},{"move":{"name":"swagger"}},{"move":{"name":"sleep-talk"}},{"move":{"name":"return"}},{"move":{"name":"frustration"}},{"move":{"name":"safeguard"}},{"move":{"name":"rapid-spin"}},{"move":{"name":"hidden-power"}},{"move":{"name":"rain-dance"}},{"move":{"name":"sunny-day"}},{"move":{"name":"psych-up"}},{"move":{"name":"ancient-power"}},{"move":{"name":"shadow-ball"}},{"move":{"name":"future-sight"}},{"move":{"name":"rock-smash"}},{"move":{"name":"facade"}},{"move":{"name":"trick"}},{"move":{"name":"magic-coat"}},{"move":{"name":"recycle"}},{"move":{"name":"skill-swap"}},{"move":{"name":"imprison"}},{"move":{"name":"secret-power"}},{"move":{"name":"rock-tomb"}},{"move":{"name":"cosmic-power"}},{"move":{"name":"signal-beam"}},{"move":{"name":"extrasensory"}},{"move":{"name":"sand-tomb"}},{"move":{"name":"iron-defense"}},{"move":{"name":"calm-mind"}},{"move":{"name":"gravity"}},{"move":{"name":"gyro-ball"}},{"move":{"name":"natural-gift"}},{"move":{"name":"heal-block"}},{"move":{"name":"power-trick"}},{"move":{"name":"power-swap"}},{"move":{"name":"guard-swap"}},{"move":{"name":"rock-polish"}},{"move":{"name":"earth-power"}},{"move":{"name":"giga-impact"}},{"move":{"name":"nasty-plot"}},{"move":{"name":"zen-headbutt"}},{"move":{"name":"trick-room"}},{"move":{"name":"stone-edge"}},{"move":{"name":"stealth-rock"}},{"move":{"name":"grass-knot"}},{"move":{"name":"charge-beam"}},{"move":{"name":"guard-split"}},{"move":{"name":"power-split"}},{"move":{"name":"wonder-room"}},{"move":{"name":"psyshock"}},{"move":{"name":"telekinesis"}},{"move":{"name":"smack-down"}},{"move":{"name":"round"}},{"move":{"name":"stored-power"}},{"move":{"name":"ally-switch"}},{"move":{"name":"hex"}},{"move":{"name":"bulldoze"}},{"move":{"name":"drill-run"}},{"move":{"name":"confide"}},{"move":{"name":"eerie-impulse"}},{"move":{"name":"dazzling-gleam"}},{"move":{"name":"psychic-terrain"}},{"move":{"name":"body-press"}},{"move":{"name":"expanding-force"}},{"move":{"name":"scorching-sands"}}],"name":"claydol","order":457,"species":{"name":"claydol"},"sprites":{"other":{"dream_world":{"front_default":"https://raw.githubusercontent.com/PokeAPI/sprites/master/sprites/pokemon/other/dream-world/344.svg","front_female":null},"home":{"front_default":"https://raw.githubusercontent.com/PokeAPI/sprites/master/sprites/pokemon/other/home/344.png","front_female":null,"front_shiny":"https://raw.githubusercontent.com/PokeAPI/sprites/master/sprites/pokemon/other/home/shiny/344.png","front_shiny_female":null},"official-artwork":{"front_default":"https://raw.githubusercontent.com/PokeAPI/sprites/master/sprites/pokemon/other/official-artwork/344.png","front_shiny":"https://raw.githubusercontent.com/PokeAPI/sprites/master/sprites/pokemon/other/official-artwork/shiny/344.png"}}},"types":[{"slot":1,"type":{"name":"ground","url":"https://pokeapi.co/api/v2/type/5/"}},{"slot":2,"type":{"name":"psychic","url":"https://pokeapi.co/api/v2/type/14/"}}],"weight":1080}
