{"abilities":[{"ability":{"name":"levitate"},"is_hidden":false,"slot":1}],"game_indices":[{"version":{"name":"black"}},{"version":{"name":"white"}},{"version":{"name":"black-2"}},{"version":{"name":"white-2"}}],"height":11,"id":615,"moves":[{"move":{"name":"bind"}},{"move":{"name":"body-slam"}},{"move":{"name":"take-down"}},{"move":{"name":"mist"}},{"move":{"name":"ice-beam"}},{"move":{"name":"blizzard"}},{"move":{"name":"aurora-beam"}},{"move":{"name":"hyper-beam"}},{"move":{"name":"solar-beam"}},{"move":{"name":"toxic"}},{"move":{"name":"double-team"}},{"move":{"name":"recover"}},{"move":{"name":"confuse-ray"}},{"move":{"name":"light-screen"}},{"move":{"name":"haze"}},{"move":{"name":"reflect"}},{"move":{"name":"self-destruct"}},{"move":{"name":"acid-armor"}},{"move":{"name":"explosion"}},{"move":{"name":"rest"}},{"move":{"name":"sharpen"}},{"move":{"name":"slash"}},{"move":{"name":"substitute"}},{"move":{"name":"snore"}},{"move":{"name":"protect"}},{"move":{"name":"scary-face"}},{"move":{"name":"icy-wind"}},{"move":{"name":"endure"}},{"move":{"name":"swagger"}},{"move":{"name":"attract"}},{"move":{"name":"sleep-talk"}},{"move":{"name":"return"}},{"move":{"name":"frustration"}},{"move":{"name":"rapid-spin"}},{"move":{"name":"hidden-power"}},{"move":{"name":"rain-dance"}},{"move":{"name":"ancient-power"}},{"move":{"name":"hail"}},{"move":{"name":"facade"}},{"move":{"name":"magic-coat"}},{"move":{"name":"knock-off"}},{"move":{"name":"secret-power"}},{"move":{"name":"signal-beam"}},{"move":{"name":"sheer-cold"}},{"move":{"name":"icicle-spear"}},{"move":{"name":"iron-defense"}},{"move":{"name":"water-pulse"}},{"move":{"name":"poison-jab"}},{"move":{"name":"night-slash"}},{"move":{"name":"giga-impact"}},{"move":{"name":"avalanche"}},{"move":{"name":"ice-shard"}},{"move":{"name":"flash-cannon"}},{"move":{"name":"defog"}},{"move":{"name":"round"}},{"move":{"name":"acrobatics"}},{"move":{"name":"frost-breath"}},{"move":{"name":"freeze-dry"}},{"move":{"name":"confide"}},{"move":{"name":"laser-focus"}},{"move":{"name":"aurora-veil"}},{"move":{"name":"triple-axel"}},{"move":{"name":"tera-blast"}},{"move":{"name":"ice-spinner"}},{"move":{"name":"snowscape"}},{"move":{"name":"chilling-water"}}],"name":"cryogonal","order":737,"species":{"name":"cryogonal"},"sprites":{"other":{"dream_world":{"front_default":"https://raw.githubusercontent.com/PokeAPI/sprites/master/sprites/pokemon/other/dream-world/615.svg","front_female":null},"home":{"front_default":"https://raw.githubusercontent.com/PokeAPI/sprites/master/sprites/pokemon/other/home/615.png","front_female":null,"front_shiny":"https://raw.githubusercontent.com/PokeAPI/sprites/master/sprites/pokemon/other/home/shiny/615.png","front_shiny_female":null},"official-artwork":{"front_default":"https://raw.githubusercontent.com/PokeAPI/sprites/master/sprites/pokemon/other/official-artwork/615.png","front_shiny":"https://raw.githubusercontent.com/PokeAPI/sprites/master/sprites/pokemon/other/official-artwork/shiny/615.png"}}},"types":[{"slot":1,"type":{"name":"ice","url":"https://pokeapi.co/api/v2/type/15/"}}],"weight":1480}
